{
    "windows": [
        {
            "emotePopup": {
                "x": 976,
                "y": 491
            },
            "height": 1586,
            "tabs": [
                {
                    "highlightsEnabled": true,
                    "selected": true,
                    "splits2": {
                        "flexh": 1,
                        "flexv": 1,
                        "items": [
                            {
                                "data": {
                                    "name": "okabar",
                                    "type": "twitch"
                                },
                                "filters": [
                                    "295bd4aa-a84f-4a53-82ac-f0cef14f8595"
                                ],
                                "flexh": 1.0117974032635026,
                                "flexv": 1,
                                "moderationMode": false,
                                "type": "split"
                            },
                            {
                                "flexh": 1.0076336279414306,
                                "flexv": 1,
                                "items": [
                                    {
                                        "data": {
                                            "name": "visioisiv",
                                            "type": "twitch"
                                        },
                                        "filters": [
                                        ],
                                        "flexh": 1,
                                        "flexv": 1,
                                        "moderationMode": false,
                                        "type": "split"
                                    },
                                    {
                                        "data": {
                                            "name": "lilbint",
                                            "type": "twitch"
                                        },
                                        "filters": [
                                        ],
                                        "flexh": 1,
                                        "flexv": 1,
                                        "moderationMode": false,
                                        "type": "split"
                                    }
                                ],
                                "type": "vertical"
                            },
                            {
                                "flexh": 0.9805689687950665,
                                "flexv": 1,
                                "items": [
                                    {
                                        "data": {
                                            "type": "mentions"
                                        },
                                        "filters": [
                                        ],
                                        "flexh": 1,
                                        "flexv": 1,
                                        "moderationMode": false,
                                        "type": "split"
                                    },
                                    {
                                        "data": {
                                            "name": "darkvypr",
                                            "type": "twitch"
                                        },
                                        "filters": [
                                        ],
                                        "flexh": 1,
                                        "flexv": 1,
                                        "moderationMode": false,
                                        "type": "split"
                                    }
                                ],
                                "type": "vertical"
                            }
                        ],
                        "type": "horizontal"
                    },
                    "title": "main"
                },
                {
                    "highlightsEnabled": false,
                    "splits2": {
                        "flexh": 1,
                        "flexv": 1,
                        "items": [
                            {
                                "data": {
                                    "name": "xqcow",
                                    "type": "twitch"
                                },
                                "filters": [
                                    "295bd4aa-a84f-4a53-82ac-f0cef14f8595",
                                    "32e4efa9-a66b-41f6-a961-c9f9db3fd7c9",
                                    "8808c65d-aa06-4515-97f9-e6b1c3295f68",
                                    "a81e952b-339b-4653-af37-de631e9219fa",
                                    "f34e0062-f7ad-44f5-823a-78c781e0cf9a"
                                ],
                                "flexh": 1,
                                "flexv": 1,
                                "moderationMode": false,
                                "type": "split"
                            },
                            {
                                "flexh": 1.005213764337852,
                                "flexv": 1,
                                "items": [
                                    {
                                        "data": {
                                            "name": "visioisiv",
                                            "type": "twitch"
                                        },
                                        "filters": [
                                        ],
                                        "flexh": 1,
                                        "flexv": 1,
                                        "moderationMode": false,
                                        "type": "split"
                                    },
                                    {
                                        "data": {
                                            "name": "okabar",
                                            "type": "twitch"
                                        },
                                        "filters": [
                                        ],
                                        "flexh": 1,
                                        "flexv": 1,
                                        "moderationMode": false,
                                        "type": "split"
                                    }
                                ],
                                "type": "vertical"
                            },
                            {
                                "flexh": 0.994786235662148,
                                "flexv": 1,
                                "items": [
                                    {
                                        "data": {
                                            "type": "mentions"
                                        },
                                        "filters": [
                                        ],
                                        "flexh": 1,
                                        "flexv": 1,
                                        "moderationMode": false,
                                        "type": "split"
                                    },
                                    {
                                        "data": {
                                            "name": "darkvypr",
                                            "type": "twitch"
                                        },
                                        "filters": [
                                        ],
                                        "flexh": 1,
                                        "flexv": 1,
                                        "moderationMode": false,
                                        "type": "split"
                                    }
                                ],
                                "type": "vertical"
                            }
                        ],
                        "type": "horizontal"
                    },
                    "title": "xqc"
                },
                {
                    "highlightsEnabled": true,
                    "splits2": {
                        "flexh": 1,
                        "flexv": 1,
                        "items": [
                            {
                                "data": {
                                    "name": "elis",
                                    "type": "twitch"
                                },
                                "filters": [
                                ],
                                "flexh": 1.0083333333333333,
                                "flexv": 1,
                                "moderationMode": false,
                                "type": "split"
                            },
                            {
                                "flexh": 0.9916666666666667,
                                "flexv": 1,
                                "items": [
                                    {
                                        "data": {
                                            "name": "visioisiv",
                                            "type": "twitch"
                                        },
                                        "filters": [
                                        ],
                                        "flexh": 1,
                                        "flexv": 1,
                                        "moderationMode": false,
                                        "type": "split"
                                    },
                                    {
                                        "data": {
                                            "name": "okabar",
                                            "type": "twitch"
                                        },
                                        "filters": [
                                        ],
                                        "flexh": 1,
                                        "flexv": 1,
                                        "moderationMode": false,
                                        "type": "split"
                                    },
                                    {
                                        "data": {
                                            "name": "lilbint",
                                            "type": "twitch"
                                        },
                                        "filters": [
                                        ],
                                        "flexh": 1,
                                        "flexv": 1,
                                        "moderationMode": false,
                                        "type": "split"
                                    }
                                ],
                                "type": "vertical"
                            },
                            {
                                "flexh": 1,
                                "flexv": 1,
                                "items": [
                                    {
                                        "data": {
                                            "type": "mentions"
                                        },
                                        "filters": [
                                        ],
                                        "flexh": 1,
                                        "flexv": 1,
                                        "moderationMode": false,
                                        "type": "split"
                                    },
                                    {
                                        "data": {
                                            "name": "darkvypr",
                                            "type": "twitch"
                                        },
                                        "filters": [
                                        ],
                                        "flexh": 1,
                                        "flexv": 1,
                                        "moderationMode": false,
                                        "type": "split"
                                    }
                                ],
                                "type": "vertical"
                            }
                        ],
                        "type": "horizontal"
                    },
                    "title": "elis"
                },
                {
                    "highlightsEnabled": false,
                    "splits2": {
                        "flexh": 1,
                        "flexv": 1,
                        "items": [
                            {
                                "data": {
                                    "name": "munibug",
                                    "type": "twitch"
                                },
                                "filters": [
                                ],
                                "flexh": 1,
                                "flexv": 1,
                                "moderationMode": false,
                                "type": "split"
                            },
                            {
                                "flexh": 1,
                                "flexv": 1,
                                "items": [
                                    {
                                        "data": {
                                            "name": "okabar",
                                            "type": "twitch"
                                        },
                                        "filters": [
                                        ],
                                        "flexh": 1,
                                        "flexv": 1,
                                        "moderationMode": false,
                                        "type": "split"
                                    },
                                    {
                                        "data": {
                                            "name": "maiman",
                                            "type": "twitch"
                                        },
                                        "filters": [
                                        ],
                                        "flexh": 1,
                                        "flexv": 1,
                                        "moderationMode": false,
                                        "type": "split"
                                    }
                                ],
                                "type": "vertical"
                            },
                            {
                                "flexh": 1,
                                "flexv": 1,
                                "items": [
                                    {
                                        "data": {
                                            "type": "mentions"
                                        },
                                        "filters": [
                                        ],
                                        "flexh": 1,
                                        "flexv": 1,
                                        "moderationMode": false,
                                        "type": "split"
                                    },
                                    {
                                        "data": {
                                            "name": "darkvypr",
                                            "type": "twitch"
                                        },
                                        "filters": [
                                        ],
                                        "flexh": 1,
                                        "flexv": 1,
                                        "moderationMode": false,
                                        "type": "split"
                                    }
                                ],
                                "type": "vertical"
                            }
                        ],
                        "type": "horizontal"
                    },
                    "title": "muni"
                },
                {
                    "highlightsEnabled": true,
                    "splits2": {
                        "flexh": 1,
                        "flexv": 1,
                        "items": [
                            {
                                "data": {
                                    "name": "vexnade",
                                    "type": "twitch"
                                },
                                "filters": [
                                ],
                                "flexh": 1,
                                "flexv": 1,
                                "moderationMode": false,
                                "type": "split"
                            },
                            {
                                "data": {
                                    "name": "imz_loading",
                                    "type": "twitch"
                                },
                                "filters": [
                                ],
                                "flexh": 1,
                                "flexv": 1,
                                "moderationMode": false,
                                "type": "split"
                            }
                        ],
                        "type": "horizontal"
                    },
                    "title": "bot"
                },
                {
                    "highlightsEnabled": true,
                    "splits2": {
                        "flexh": 1,
                        "flexv": 1,
                        "items": [
                            {
                                "flexh": 1,
                                "flexv": 1,
                                "items": [
                                    {
                                        "data": {
                                            "name": "zreem",
                                            "type": "twitch"
                                        },
                                        "filters": [
                                        ],
                                        "flexh": 1,
                                        "flexv": 1,
                                        "moderationMode": false,
                                        "type": "split"
                                    },
                                    {
                                        "data": {
                                            "name": "nozav",
                                            "type": "twitch"
                                        },
                                        "filters": [
                                        ],
                                        "flexh": 1,
                                        "flexv": 1,
                                        "moderationMode": false,
                                        "type": "split"
                                    }
                                ],
                                "type": "vertical"
                            },
                            {
                                "flexh": 1,
                                "flexv": 1,
                                "items": [
                                    {
                                        "data": {
                                            "name": "okabar",
                                            "type": "twitch"
                                        },
                                        "filters": [
                                        ],
                                        "flexh": 1,
                                        "flexv": 1,
                                        "moderationMode": false,
                                        "type": "split"
                                    },
                                    {
                                        "data": {
                                            "name": "maiman",
                                            "type": "twitch"
                                        },
                                        "filters": [
                                        ],
                                        "flexh": 1,
                                        "flexv": 1,
                                        "moderationMode": false,
                                        "type": "split"
                                    }
                                ],
                                "type": "vertical"
                            },
                            {
                                "flexh": 1,
                                "flexv": 1,
                                "items": [
                                    {
                                        "data": {
                                            "type": "mentions"
                                        },
                                        "filters": [
                                        ],
                                        "flexh": 1,
                                        "flexv": 1,
                                        "moderationMode": false,
                                        "type": "split"
                                    },
                                    {
                                        "data": {
                                            "name": "darkvypr",
                                            "type": "twitch"
                                        },
                                        "filters": [
                                        ],
                                        "flexh": 1,
                                        "flexv": 1,
                                        "moderationMode": false,
                                        "type": "split"
                                    }
                                ],
                                "type": "vertical"
                            }
                        ],
                        "type": "horizontal"
                    },
                    "title": "zreem+noazv"
                },
                {
                    "highlightsEnabled": true,
                    "splits2": {
                        "flexh": 1,
                        "flexv": 1,
                        "items": [
                            {
                                "flexh": 1,
                                "flexv": 1,
                                "items": [
                                    {
                                        "data": {
                                            "name": "nmplol",
                                            "type": "twitch"
                                        },
                                        "filters": [
                                        ],
                                        "flexh": 1,
                                        "flexv": 1,
                                        "moderationMode": false,
                                        "type": "split"
                                    },
                                    {
                                        "data": {
                                            "name": "hottemperz",
                                            "type": "twitch"
                                        },
                                        "filters": [
                                        ],
                                        "flexh": 1,
                                        "flexv": 1,
                                        "moderationMode": false,
                                        "type": "split"
                                    }
                                ],
                                "type": "vertical"
                            },
                            {
                                "flexh": 1,
                                "flexv": 1,
                                "items": [
                                    {
                                        "data": {
                                            "name": "okabar",
                                            "type": "twitch"
                                        },
                                        "filters": [
                                        ],
                                        "flexh": 1,
                                        "flexv": 1,
                                        "moderationMode": false,
                                        "type": "split"
                                    },
                                    {
                                        "data": {
                                            "name": "maiman",
                                            "type": "twitch"
                                        },
                                        "filters": [
                                        ],
                                        "flexh": 1,
                                        "flexv": 1,
                                        "moderationMode": false,
                                        "type": "split"
                                    }
                                ],
                                "type": "vertical"
                            },
                            {
                                "flexh": 1,
                                "flexv": 1,
                                "items": [
                                    {
                                        "data": {
                                            "type": "mentions"
                                        },
                                        "filters": [
                                        ],
                                        "flexh": 1,
                                        "flexv": 1,
                                        "moderationMode": false,
                                        "type": "split"
                                    },
                                    {
                                        "data": {
                                            "name": "darkvypr",
                                            "type": "twitch"
                                        },
                                        "filters": [
                                        ],
                                        "flexh": 1,
                                        "flexv": 1,
                                        "moderationMode": false,
                                        "type": "split"
                                    }
                                ],
                                "type": "vertical"
                            }
                        ],
                        "type": "horizontal"
                    },
                    "title": "nmp+temp"
                },
                {
                    "highlightsEnabled": true,
                    "splits2": {
                        "flexh": 1,
                        "flexv": 1,
                        "items": [
                            {
                                "flexh": 1,
                                "flexv": 1,
                                "items": [
                                    {
                                        "data": {
                                            "name": "godemperoraxo",
                                            "type": "twitch"
                                        },
                                        "filters": [
                                        ],
                                        "flexh": 1,
                                        "flexv": 0.9730085582620145,
                                        "moderationMode": false,
                                        "type": "split"
                                    },
                                    {
                                        "data": {
                                            "name": "alte",
                                            "type": "twitch"
                                        },
                                        "filters": [
                                        ],
                                        "flexh": 1,
                                        "flexv": 1.0269914417379855,
                                        "moderationMode": false,
                                        "type": "split"
                                    }
                                ],
                                "type": "vertical"
                            },
                            {
                                "flexh": 1.0135275754422477,
                                "flexv": 1,
                                "items": [
                                    {
                                        "data": {
                                            "name": "okabar",
                                            "type": "twitch"
                                        },
                                        "filters": [
                                        ],
                                        "flexh": 1,
                                        "flexv": 1,
                                        "moderationMode": false,
                                        "type": "split"
                                    },
                                    {
                                        "data": {
                                            "name": "maiman",
                                            "type": "twitch"
                                        },
                                        "filters": [
                                        ],
                                        "flexh": 1,
                                        "flexv": 1,
                                        "moderationMode": false,
                                        "type": "split"
                                    }
                                ],
                                "type": "vertical"
                            },
                            {
                                "flexh": 0.9864724245577523,
                                "flexv": 1,
                                "items": [
                                    {
                                        "data": {
                                            "type": "mentions"
                                        },
                                        "filters": [
                                        ],
                                        "flexh": 1,
                                        "flexv": 1,
                                        "moderationMode": false,
                                        "type": "split"
                                    },
                                    {
                                        "data": {
                                            "name": "darkvypr",
                                            "type": "twitch"
                                        },
                                        "filters": [
                                        ],
                                        "flexh": 1,
                                        "flexv": 1,
                                        "moderationMode": false,
                                        "type": "split"
                                    }
                                ],
                                "type": "vertical"
                            }
                        ],
                        "type": "horizontal"
                    },
                    "title": "alte+axo"
                },
                {
                    "highlightsEnabled": false,
                    "splits2": {
                        "flexh": 1,
                        "flexv": 1,
                        "items": [
                            {
                                "flexh": 1,
                                "flexv": 1,
                                "items": [
                                    {
                                        "data": {
                                            "name": "genialasp",
                                            "type": "twitch"
                                        },
                                        "filters": [
                                        ],
                                        "flexh": 1,
                                        "flexv": 1,
                                        "moderationMode": false,
                                        "type": "split"
                                    },
                                    {
                                        "data": {
                                            "name": "bubbabunyip",
                                            "type": "twitch"
                                        },
                                        "filters": [
                                        ],
                                        "flexh": 1,
                                        "flexv": 1,
                                        "moderationMode": false,
                                        "type": "split"
                                    }
                                ],
                                "type": "vertical"
                            },
                            {
                                "flexh": 1,
                                "flexv": 1,
                                "items": [
                                    {
                                        "data": {
                                            "name": "okabar",
                                            "type": "twitch"
                                        },
                                        "filters": [
                                        ],
                                        "flexh": 1,
                                        "flexv": 1,
                                        "moderationMode": false,
                                        "type": "split"
                                    },
                                    {
                                        "data": {
                                            "name": "maiman",
                                            "type": "twitch"
                                        },
                                        "filters": [
                                        ],
                                        "flexh": 1,
                                        "flexv": 1,
                                        "moderationMode": false,
                                        "type": "split"
                                    }
                                ],
                                "type": "vertical"
                            },
                            {
                                "flexh": 1,
                                "flexv": 1,
                                "items": [
                                    {
                                        "data": {
                                            "type": "mentions"
                                        },
                                        "filters": [
                                        ],
                                        "flexh": 1,
                                        "flexv": 1,
                                        "moderationMode": false,
                                        "type": "split"
                                    },
                                    {
                                        "data": {
                                            "name": "darkvypr",
                                            "type": "twitch"
                                        },
                                        "filters": [
                                        ],
                                        "flexh": 1,
                                        "flexv": 1,
                                        "moderationMode": false,
                                        "type": "split"
                                    }
                                ],
                                "type": "vertical"
                            }
                        ],
                        "type": "horizontal"
                    },
                    "title": "bubba+geni"
                },
                {
                    "highlightsEnabled": true,
                    "splits2": {
                        "flexh": 1,
                        "flexv": 1,
                        "items": [
                            {
                                "flexh": 1,
                                "flexv": 1,
                                "items": [
                                    {
                                        "data": {
                                            "name": "snowstormcs",
                                            "type": "twitch"
                                        },
                                        "filters": [
                                        ],
                                        "flexh": 1,
                                        "flexv": 1,
                                        "moderationMode": false,
                                        "type": "split"
                                    },
                                    {
                                        "data": {
                                            "name": "eazylemnsqeezy",
                                            "type": "twitch"
                                        },
                                        "filters": [
                                        ],
                                        "flexh": 1,
                                        "flexv": 1,
                                        "moderationMode": false,
                                        "type": "split"
                                    }
                                ],
                                "type": "vertical"
                            },
                            {
                                "flexh": 1,
                                "flexv": 1,
                                "items": [
                                    {
                                        "data": {
                                            "name": "okabar",
                                            "type": "twitch"
                                        },
                                        "filters": [
                                        ],
                                        "flexh": 1,
                                        "flexv": 1,
                                        "moderationMode": false,
                                        "type": "split"
                                    },
                                    {
                                        "data": {
                                            "name": "maiman",
                                            "type": "twitch"
                                        },
                                        "filters": [
                                        ],
                                        "flexh": 1,
                                        "flexv": 1,
                                        "moderationMode": false,
                                        "type": "split"
                                    }
                                ],
                                "type": "vertical"
                            },
                            {
                                "flexh": 1,
                                "flexv": 1,
                                "items": [
                                    {
                                        "data": {
                                            "type": "mentions"
                                        },
                                        "filters": [
                                        ],
                                        "flexh": 1,
                                        "flexv": 1,
                                        "moderationMode": false,
                                        "type": "split"
                                    },
                                    {
                                        "data": {
                                            "name": "darkvypr",
                                            "type": "twitch"
                                        },
                                        "filters": [
                                        ],
                                        "flexh": 1,
                                        "flexv": 1,
                                        "moderationMode": false,
                                        "type": "split"
                                    }
                                ],
                                "type": "vertical"
                            }
                        ],
                        "type": "horizontal"
                    },
                    "title": "eazy+snowwy"
                },
                {
                    "highlightsEnabled": true,
                    "splits2": {
                        "flexh": 1,
                        "flexv": 1,
                        "items": [
                            {
                                "data": {
                                    "name": "vyprbot",
                                    "type": "twitch"
                                },
                                "filters": [
                                ],
                                "flexh": 1,
                                "flexv": 1,
                                "moderationMode": false,
                                "type": "split"
                            },
                            {
                                "flexh": 1.0371423752775337,
                                "flexv": 1,
                                "items": [
                                    {
                                        "data": {
                                            "name": "visioisiv",
                                            "type": "twitch"
                                        },
                                        "filters": [
                                        ],
                                        "flexh": 1,
                                        "flexv": 1,
                                        "moderationMode": false,
                                        "type": "split"
                                    },
                                    {
                                        "data": {
                                            "name": "okabar",
                                            "type": "twitch"
                                        },
                                        "filters": [
                                        ],
                                        "flexh": 1,
                                        "flexv": 1,
                                        "moderationMode": false,
                                        "type": "split"
                                    }
                                ],
                                "type": "vertical"
                            },
                            {
                                "flexh": 0.9628576247224665,
                                "flexv": 1,
                                "items": [
                                    {
                                        "data": {
                                            "type": "mentions"
                                        },
                                        "filters": [
                                        ],
                                        "flexh": 1,
                                        "flexv": 0.9142519219396806,
                                        "moderationMode": false,
                                        "type": "split"
                                    },
                                    {
                                        "data": {
                                            "name": "darkvypr",
                                            "type": "twitch"
                                        },
                                        "filters": [
                                        ],
                                        "flexh": 1,
                                        "flexv": 1.0857480780603193,
                                        "moderationMode": false,
                                        "type": "split"
                                    }
                                ],
                                "type": "vertical"
                            }
                        ],
                        "type": "horizontal"
                    },
                    "title": "variable"
                },
                {
                    "highlightsEnabled": false,
                    "splits2": {
                        "flexh": 1,
                        "flexv": 1,
                        "items": [
                            {
                                "flexh": 1.0156739811912228,
                                "flexv": 1,
                                "items": [
                                    {
                                        "data": {
                                            "name": "pokelawls",
                                            "type": "twitch"
                                        },
                                        "filters": [
                                        ],
                                        "flexh": 1,
                                        "flexv": 1,
                                        "moderationMode": false,
                                        "type": "split"
                                    },
                                    {
                                        "data": {
                                            "name": "oathmeal",
                                            "type": "twitch"
                                        },
                                        "filters": [
                                        ],
                                        "flexh": 1,
                                        "flexv": 1,
                                        "moderationMode": false,
                                        "type": "split"
                                    },
                                    {
                                        "data": {
                                            "name": "verniy",
                                            "type": "twitch"
                                        },
                                        "filters": [
                                        ],
                                        "flexh": 1,
                                        "flexv": 1,
                                        "moderationMode": false,
                                        "type": "split"
                                    },
                                    {
                                        "data": {
                                            "name": "redshell",
                                            "type": "twitch"
                                        },
                                        "filters": [
                                        ],
                                        "flexh": 1,
                                        "flexv": 1,
                                        "moderationMode": false,
                                        "type": "split"
                                    },
                                    {
                                        "data": {
                                            "name": "eeveelinh",
                                            "type": "twitch"
                                        },
                                        "filters": [
                                        ],
                                        "flexh": 1,
                                        "flexv": 1,
                                        "moderationMode": false,
                                        "type": "split"
                                    }
                                ],
                                "type": "vertical"
                            },
                            {
                                "flexh": 0.9921630094043887,
                                "flexv": 1,
                                "items": [
                                    {
                                        "data": {
                                            "name": "astro",
                                            "type": "twitch"
                                        },
                                        "filters": [
                                        ],
                                        "flexh": 1,
                                        "flexv": 1.1016187050359711,
                                        "moderationMode": false,
                                        "type": "split"
                                    },
                                    {
                                        "data": {
                                            "name": "veibae",
                                            "type": "twitch"
                                        },
                                        "filters": [
                                        ],
                                        "flexh": 1,
                                        "flexv": 0.7688848920863309,
                                        "moderationMode": false,
                                        "type": "split"
                                    },
                                    {
                                        "data": {
                                            "name": "trainwreckstv",
                                            "type": "twitch"
                                        },
                                        "filters": [
                                        ],
                                        "flexh": 1,
                                        "flexv": 0.9262589928057556,
                                        "moderationMode": false,
                                        "type": "split"
                                    },
                                    {
                                        "data": {
                                            "name": "gabs",
                                            "type": "twitch"
                                        },
                                        "filters": [
                                        ],
                                        "flexh": 1,
                                        "flexv": 1.1016187050359711,
                                        "moderationMode": false,
                                        "type": "split"
                                    },
                                    {
                                        "data": {
                                            "name": "hana",
                                            "type": "twitch"
                                        },
                                        "filters": [
                                        ],
                                        "flexh": 1,
                                        "flexv": 1.1016187050359711,
                                        "moderationMode": false,
                                        "type": "split"
                                    }
                                ],
                                "type": "vertical"
                            },
                            {
                                "flexh": 0.9921630094043887,
                                "flexv": 1,
                                "items": [
                                    {
                                        "data": {
                                            "name": "august",
                                            "type": "twitch"
                                        },
                                        "filters": [
                                        ],
                                        "flexh": 1,
                                        "flexv": 1,
                                        "moderationMode": false,
                                        "type": "split"
                                    },
                                    {
                                        "data": {
                                            "name": "naro",
                                            "type": "twitch"
                                        },
                                        "filters": [
                                        ],
                                        "flexh": 1,
                                        "flexv": 1,
                                        "moderationMode": false,
                                        "type": "split"
                                    },
                                    {
                                        "data": {
                                            "name": "zealryth",
                                            "type": "twitch"
                                        },
                                        "filters": [
                                        ],
                                        "flexh": 1,
                                        "flexv": 1,
                                        "moderationMode": false,
                                        "type": "split"
                                    },
                                    {
                                        "data": {
                                            "name": "pigeoncarbon",
                                            "type": "twitch"
                                        },
                                        "filters": [
                                        ],
                                        "flexh": 1,
                                        "flexv": 1,
                                        "moderationMode": false,
                                        "type": "split"
                                    }
                                ],
                                "type": "vertical"
                            }
                        ],
                        "type": "horizontal"
                    },
                    "title": "viewerlist"
                },
                {
                    "highlightsEnabled": true,
                    "splits2": {
                        "flexh": 1,
                        "flexv": 1,
                        "items": [
                            {
                                "flexh": 1,
                                "flexv": 1,
                                "items": [
                                    {
                                        "data": {
                                            "name": "unbotherd2",
                                            "type": "twitch"
                                        },
                                        "filters": [
                                        ],
                                        "flexh": 1,
                                        "flexv": 1,
                                        "moderationMode": false,
                                        "type": "split"
                                    },
                                    {
                                        "data": {
                                            "name": "slurpoh",
                                            "type": "twitch"
                                        },
                                        "filters": [
                                        ],
                                        "flexh": 1,
                                        "flexv": 1.032596685082873,
                                        "moderationMode": false,
                                        "type": "split"
                                    },
                                    {
                                        "data": {
                                            "name": "xenoplopqb",
                                            "type": "twitch"
                                        },
                                        "filters": [
                                        ],
                                        "flexh": 1,
                                        "flexv": 0.9348066298342541,
                                        "moderationMode": false,
                                        "type": "split"
                                    },
                                    {
                                        "data": {
                                            "name": "happytoaster_",
                                            "type": "twitch"
                                        },
                                        "filters": [
                                        ],
                                        "flexh": 1,
                                        "flexv": 1.032596685082873,
                                        "moderationMode": false,
                                        "type": "split"
                                    }
                                ],
                                "type": "vertical"
                            },
                            {
                                "flexh": 1,
                                "flexv": 1,
                                "items": [
                                    {
                                        "data": {
                                            "name": "nekraad",
                                            "type": "twitch"
                                        },
                                        "filters": [
                                        ],
                                        "flexh": 1,
                                        "flexv": 1,
                                        "moderationMode": false,
                                        "type": "split"
                                    },
                                    {
                                        "data": {
                                            "name": "ike_tx",
                                            "type": "twitch"
                                        },
                                        "filters": [
                                        ],
                                        "flexh": 1,
                                        "flexv": 1,
                                        "moderationMode": false,
                                        "type": "split"
                                    },
                                    {
                                        "data": {
                                            "name": "frocasso",
                                            "type": "twitch"
                                        },
                                        "filters": [
                                        ],
                                        "flexh": 1,
                                        "flexv": 1,
                                        "moderationMode": false,
                                        "type": "split"
                                    },
                                    {
                                        "data": {
                                            "name": "velpux",
                                            "type": "twitch"
                                        },
                                        "filters": [
                                        ],
                                        "flexh": 1,
                                        "flexv": 1,
                                        "moderationMode": false,
                                        "type": "split"
                                    },
                                    {
                                        "data": {
                                            "name": "hhharrisonnn",
                                            "type": "twitch"
                                        },
                                        "filters": [
                                        ],
                                        "flexh": 1,
                                        "flexv": 1,
                                        "moderationMode": false,
                                        "type": "split"
                                    }
                                ],
                                "type": "vertical"
                            },
                            {
                                "flexh": 1,
                                "flexv": 1,
                                "items": [
                                    {
                                        "data": {
                                            "name": "ktobaias",
                                            "type": "twitch"
                                        },
                                        "filters": [
                                        ],
                                        "flexh": 1,
                                        "flexv": 0.9794871794871796,
                                        "moderationMode": false,
                                        "type": "split"
                                    },
                                    {
                                        "data": {
                                            "name": "clapzygn",
                                            "type": "twitch"
                                        },
                                        "filters": [
                                        ],
                                        "flexh": 1,
                                        "flexv": 1,
                                        "moderationMode": false,
                                        "type": "split"
                                    },
                                    {
                                        "data": {
                                            "name": "zipcola",
                                            "type": "twitch"
                                        },
                                        "filters": [
                                        ],
                                        "flexh": 1,
                                        "flexv": 1.0205128205128204,
                                        "moderationMode": false,
                                        "type": "split"
                                    }
                                ],
                                "type": "vertical"
                            }
                        ],
                        "type": "horizontal"
                    },
                    "title": "homies"
                },
                {
                    "highlightsEnabled": true,
                    "splits2": {
                        "flexh": 1,
                        "flexv": 1
                    },
                    "title": "watch"
                },
                {
                    "highlightsEnabled": true,
                    "splits2": {
                        "flexh": 1,
                        "flexv": 1,
                        "items": [
                            {
                                "flexh": 1,
                                "flexv": 1,
                                "items": [
                                    {
                                        "data": {
                                            "name": "m0xyy",
                                            "type": "twitch"
                                        },
                                        "filters": [
                                        ],
                                        "flexh": 1,
                                        "flexv": 1,
                                        "moderationMode": false,
                                        "type": "split"
                                    },
                                    {
                                        "data": {
                                            "name": "cyr",
                                            "type": "twitch"
                                        },
                                        "filters": [
                                        ],
                                        "flexh": 1,
                                        "flexv": 1,
                                        "moderationMode": false,
                                        "type": "split"
                                    }
                                ],
                                "type": "vertical"
                            },
                            {
                                "flexh": 1,
                                "flexv": 1,
                                "items": [
                                    {
                                        "data": {
                                            "name": "zoil",
                                            "type": "twitch"
                                        },
                                        "filters": [
                                        ],
                                        "flexh": 1,
                                        "flexv": 1,
                                        "moderationMode": false,
                                        "type": "split"
                                    },
                                    {
                                        "data": {
                                            "name": "nymn",
                                            "type": "twitch"
                                        },
                                        "filters": [
                                        ],
                                        "flexh": 1,
                                        "flexv": 1.2256317689530687,
                                        "moderationMode": false,
                                        "type": "split"
                                    },
                                    {
                                        "data": {
                                            "name": "kattah",
                                            "type": "twitch"
                                        },
                                        "filters": [
                                        ],
                                        "flexh": 1,
                                        "flexv": 0.7743682310469313,
                                        "moderationMode": false,
                                        "type": "split"
                                    }
                                ],
                                "type": "vertical"
                            },
                            {
                                "flexh": 1,
                                "flexv": 1,
                                "items": [
                                    {
                                        "data": {
                                            "name": "sodapoppin",
                                            "type": "twitch"
                                        },
                                        "filters": [
                                        ],
                                        "flexh": 1,
                                        "flexv": 0.8485013058404116,
                                        "moderationMode": false,
                                        "type": "split"
                                    },
                                    {
                                        "data": {
                                            "name": "crazyslick",
                                            "type": "twitch"
                                        },
                                        "filters": [
                                        ],
                                        "flexh": 1,
                                        "flexv": 1.1514986941595884,
                                        "moderationMode": false,
                                        "type": "split"
                                    }
                                ],
                                "type": "vertical"
                            }
                        ],
                        "type": "horizontal"
                    },
                    "title": "rarely watch"
                }
            ],
            "type": "main",
            "width": 1442,
            "x": 2559,
            "y": 412
        }
    ]
}
